voicetotext/__init__.py
voicetotext/animation.py
voicetotext/extension.py
voicetotext/factory.py
voicetotext/prompt.py
voicetotext/splitter.py
voicetotext/splitvoice.py
voicetotext/transcribe.py
voicetotext/voicetotext.py
voicetotext-1.0.1.dist-info/DESCRIPTION.rst
voicetotext-1.0.1.dist-info/METADATA
voicetotext-1.0.1.dist-info/RECORD
voicetotext-1.0.1.dist-info/WHEEL
voicetotext-1.0.1.dist-info/entry_points.txt
voicetotext-1.0.1.dist-info/metadata.json
voicetotext-1.0.1.dist-info/top_level.txt
