Metadata-Version: 2.0
Name: voicetotext
Version: 1.0.1
Summary: Transript media file to text using google api.
Home-page: https://github.com/kztka/voicetotext
Author: kztka
Author-email: paper.sheet.kami@gmail.com
License: MIT
Platform: UNKNOWN
Classifier: Programming Language :: Python :: 3
Classifier: Programming Language :: Python :: 3.4
Classifier: Programming Language :: Python :: 3.5
Classifier: Programming Language :: Python :: 3.6
Classifier: License :: OSI Approved :: MIT License
Requires-Dist: click (==6.7)
Requires-Dist: google-api-python-client (==1.6.2)
Requires-Dist: httplib2 (==0.10.3)
Requires-Dist: oauth2client (==4.0.0)
Requires-Dist: pyasn1 (==0.2.3)
Requires-Dist: pyasn1-modules (==0.0.8)
Requires-Dist: pydub (==0.18.0)
Requires-Dist: rsa (==3.4.2)
Requires-Dist: six (==1.10.0)
Requires-Dist: uritemplate (==3.0.0)
